projectslib/__init__.py
projectslib/binary.py
projectslib/digits.py
projectslib/factors.py
projectslib/np_random_grid.py
projectslib/np_utils.py
projectslib/primes.py
projectslib/py_utils.py
projectslib-0.1.0.dist-info/WHEEL
projectslib-0.1.0.dist-info/METADATA
projectslib-0.1.0.dist-info/RECORD
